[
  {
    "id": "1",
    "name": "Cyndi Wang",
    "email": "cyndi.wang@yopmail.com",
    "emailVerified": "2023-12-10T19:53:30Z",
    "image": "/image/upload/v1702864849/user/uploads/lnj2vnu8kqiedewfdgsa.png",
    "backgroundImage": "/image/upload/v1702680551/Cloudinary_data/Users/cyndibackground.png",
    "handle": "@CindiWang",
    "description": "王心凌 Cyndi Wang"
  },
  {
    "id": "2",
    "name": "Travel Bear",
    "email": "travel.bear@yopmail.com",
    "emailVerified": "2023-12-12T18:56:55Z",
    "image": "/image/upload/v1702409080/Cloudinary_data/Users/xfmnk9uvcz7enx0dbjc6.jpg",
    "backgroundImage": "/image/upload/v1702409080/Cloudinary_data/Users/fs5ezroxpaixgr5roate.jpg",
    "handle": "@TravelBear",
    "description": "I am traveling with my buddy."
  },
  {
    "id": "3",
    "name": "",
    "email": "wenghong66@yahoo.com",
    "emailVerified": "2023-12-16T03:15:11Z",
    "image": "",
    "backgroundImage": "",
    "handle": "",
    "description": ""
  }
]
